setup.py
musical/__init__.py
musical.egg-info/PKG-INFO
musical.egg-info/SOURCES.txt
musical.egg-info/dependency_links.txt
musical.egg-info/requires.txt
musical.egg-info/top_level.txt
musical/audio/__init__.py
musical/audio/effect.py
musical/audio/encode.py
musical/audio/playback.py
musical/audio/save.py
musical/audio/source.py
musical/theory/__init__.py
musical/theory/chord.py
musical/theory/note.py
musical/theory/scale.py