Metadata-Version: 1.1
Name: musical
Version: 0.2.0
Summary: A python library for dealing with sounds and music
Home-page: https://github.com/wybiral/python-musical/
Author: Davy Wybiral
Author-email: davy.wybiral@gmail.com
License: UNKNOWN
Keywords: audio music theory synthesis
Platform: any
Classifier: Intended Audience :: Developers
Classifier: Topic :: Artistic Software
Classifier: Topic :: Multimedia :: Sound/Audio :: Sound Synthesis
